searchy/__init__.py
searchy-1.0.2.dist-info/METADATA
searchy-1.0.2.dist-info/WHEEL
searchy-1.0.2.dist-info/entry_points.txt
searchy-1.0.2.dist-info/top_level.txt
searchy-1.0.2.dist-info/RECORD
