Metadata-Version: 2.1
Name: searchy
Version: 1.0.2
Summary: Python package that allows you to search on google from commands
Author: lactua
Author-email: lactua@lactua.com
Classifier: Programming Language :: Python :: 3
Classifier: License :: OSI Approved :: MIT License
Classifier: Operating System :: OS Independent
Requires-Python: >=3.6
Requires-Dist: google
